pprintx/__init__.py
pprintx/core.py
pprintx-0.1.1.dist-info/licenses/LICENSE
pprintx-0.1.1.dist-info/METADATA
pprintx-0.1.1.dist-info/WHEEL
pprintx-0.1.1.dist-info/top_level.txt
pprintx-0.1.1.dist-info/RECORD
