Metadata-Version: 2.4
Name: pprintx
Version: 0.1.1
Summary: A styled console printer with C++ cout-like syntax and ANSI color support.
Author: Ace
License: MIT License
Project-URL: Homepage, https://github.com/yourusername/pprintx
Project-URL: Repository, https://github.com/yourusername/pprintx
Requires-Python: >=3.8
License-File: LICENSE
Requires-Dist: colorama>=0.4
Dynamic: license-file
